setup.py
yamltools.py
yamltools.egg-info/PKG-INFO
yamltools.egg-info/SOURCES.txt
yamltools.egg-info/dependency_links.txt
yamltools.egg-info/entry_points.txt
yamltools.egg-info/not-zip-safe
yamltools.egg-info/top_level.txt