Metadata-Version: 1.0
Name: yamltools
Version: 0.1
Summary: tools for dealing with YAML from command line
Home-page: UNKNOWN
Author: Andrey Popp
Author-email: 8mayday@gmail.com
License: UNKNOWN
Platform: UNKNOWN
